{".class":"MypyFile","_fullname":"qdrant_client.parallel_processor","future_import_flags":[],"is_partial_stub_package":false,"is_stub":false,"names":{".class":"SymbolTable","Any":{".class":"SymbolTableNode","cross_ref":"typing.Any","kind":"Gdef"},"BaseContext":{".class":"SymbolTableNode","cross_ref":"multiprocessing.context.BaseContext","kind":"Gdef"},"BaseProcess":{".class":"SymbolTableNode","cross_ref":"multiprocessing.process.BaseProcess","kind":"Gdef"},"BaseValue":{".class":"SymbolTableNode","cross_ref":"multiprocessing.sharedctypes.Synchronized","kind":"Gdef"},"Empty":{".class":"SymbolTableNode","cross_ref":"_queue.Empty","kind":"Gdef"},"Enum":{".class":"SymbolTableNode","cross_ref":"enum.Enum","kind":"Gdef"},"Iterable":{".class":"SymbolTableNode","cross_ref":"typing.Iterable","kind":"Gdef"},"MAX_INTERNAL_BATCH_SIZE":{".class":"SymbolTableNode","kind":"Gdef","node":{".class":"Var","flags":["is_ready","is_inferred","has_explicit_value"],"fullname":"qdrant_client.parallel_processor.MAX_INTERNAL_BATCH_SIZE","name":"MAX_INTERNAL_BATCH_SIZE","setter_type":null,"type":"builtins.int"}},"ParallelWorkerPool":{".class":"SymbolTableNode","kind":"Gdef","node":{".class":"TypeInfo","_promote":[],"abstract_attributes":[],"alt_promote":null,"bases":["builtins.object"],"dataclass_transform_spec":null,"declared_metaclass":null,"defn":{".class":"ClassDef","fullname":"qdrant_client.parallel_processor.ParallelWorkerPool","name":"ParallelWorkerPool","type_vars":[]},"deletable_attributes":[],"deprecated":null,"flags":[],"fullname":"qdrant_client.parallel_processor.ParallelWorkerPool","has_param_spec_type":false,"metaclass_type":null,"metadata":{},"module_name":"qdrant_client.parallel_processor","mro":["qdrant_client.parallel_processor.ParallelWorkerPool","builtins.object"],"names":{".class":"SymbolTable","__del__":{".class":"SymbolTableNode","kind":"Mdef","node":{".class":"FuncDef","abstract_status":0,"arg_kinds":[0],"arg_names":[null],"dataclass_transform_spec":null,"deprecated":null,"flags":["is_trivial_self"],"fullname":"qdrant_client.parallel_processor.ParallelWorkerPool.__del__","name":"__del__","type":{".class":"CallableType","arg_kinds":[0],"arg_names":[null],"arg_types":["qdrant_client.parallel_processor.ParallelWorkerPool"],"def_extras":{"first_arg":"self"},"fallback":"builtins.function","from_concatenate":false,"implicit":false,"imprecise_arg_kinds":false,"is_bound":false,"is_ellipsis_args":false,"name":"__del__ of ParallelWorkerPool","ret_type":{".class":"NoneType"},"type_guard":null,"type_is":null,"unpack_kwargs":false,"variables":[]}}},"__init__":{".class":"SymbolTableNode","kind":"Mdef","node":{".class":"FuncDef","abstract_status":0,"arg_kinds":[0,0,0,1,1],"arg_names":["self","num_workers","worker","start_method","max_internal_batch_size"],"dataclass_transform_spec":null,"deprecated":null,"flags":["is_trivial_self"],"fullname":"qdrant_client.parallel_processor.ParallelWorkerPool.__init__","name":"__init__","type":{".class":"CallableType","arg_kinds":[0,0,0,1,1],"arg_names":["self","num_workers","worker","start_method","max_internal_batch_size"],"arg_types":["qdrant_client.parallel_processor.ParallelWorkerPool","builtins.int",{".class":"TypeType","item":"qdrant_client.parallel_processor.Worker"},{".class":"UnionType","items":["builtins.str",{".class":"NoneType"}],"uses_pep604_syntax":true},"builtins.int"],"def_extras":{"first_arg":"self"},"fallback":"builtins.function","from_concatenate":false,"implicit":false,"imprecise_arg_kinds":false,"is_bound":false,"is_ellipsis_args":false,"name":"__init__ of ParallelWorkerPool","ret_type":{".class":"NoneType"},"type_guard":null,"type_is":null,"unpack_kwargs":false,"variables":[]}}},"check_worker_health":{".class":"SymbolTableNode","kind":"Mdef","node":{".class":"FuncDef","abstract_status":0,"arg_kinds":[0],"arg_names":["self"],"dataclass_transform_spec":null,"deprecated":null,"flags":["is_trivial_self"],"fullname":"qdrant_client.parallel_processor.ParallelWorkerPool.check_worker_health","name":"check_worker_health","type":{".class":"CallableType","arg_kinds":[0],"arg_names":["self"],"arg_types":["qdrant_client.parallel_processor.ParallelWorkerPool"],"def_extras":{"first_arg":"self"},"fallback":"builtins.function","from_concatenate":false,"implicit":false,"imprecise_arg_kinds":false,"is_bound":false,"is_ellipsis_args":false,"name":"check_worker_health of ParallelWorkerPool","ret_type":{".class":"NoneType"},"type_guard":null,"type_is":null,"unpack_kwargs":false,"variables":[]}}},"ctx":{".class":"SymbolTableNode","implicit":true,"kind":"Mdef","node":{".class":"Var","flags":["explicit_self_type","is_ready","is_inferred"],"fullname":"qdrant_client.parallel_processor.ParallelWorkerPool.ctx","name":"ctx","setter_type":null,"type":"multiprocessing.context.BaseContext"}},"emergency_shutdown":{".class":"SymbolTableNode","implicit":true,"kind":"Mdef","node":{".class":"Var","flags":["is_inferred"],"fullname":"qdrant_client.parallel_processor.ParallelWorkerPool.emergency_shutdown","name":"emergency_shutdown","setter_type":null,"type":"builtins.bool"}},"input_queue":{".class":"SymbolTableNode","implicit":true,"kind":"Mdef","node":{".class":"Var","flags":["explicit_self_type","is_ready","is_inferred"],"fullname":"qdrant_client.parallel_processor.ParallelWorkerPool.input_queue","name":"input_queue","setter_type":null,"type":{".class":"UnionType","items":[{".class":"Instance","args":[{".class":"AnyType","missing_import_name":null,"source_any":null,"type_of_any":4}],"extra_attrs":null,"type_ref":"multiprocessing.queues.Queue"},{".class":"NoneType"}],"uses_pep604_syntax":true}}},"join":{".class":"SymbolTableNode","kind":"Mdef","node":{".class":"FuncDef","abstract_status":0,"arg_kinds":[0],"arg_names":["self"],"dataclass_transform_spec":null,"deprecated":null,"flags":["is_trivial_self"],"fullname":"qdrant_client.parallel_processor.ParallelWorkerPool.join","name":"join","type":{".class":"CallableType","arg_kinds":[0],"arg_names":["self"],"arg_types":["qdrant_client.parallel_processor.ParallelWorkerPool"],"def_extras":{"first_arg":"self"},"fallback":"builtins.function","from_concatenate":false,"implicit":false,"imprecise_arg_kinds":false,"is_bound":false,"is_ellipsis_args":false,"name":"join of ParallelWorkerPool","ret_type":{".class":"NoneType"},"type_guard":null,"type_is":null,"unpack_kwargs":false,"variables":[]}}},"join_or_terminate":{".class":"SymbolTableNode","kind":"Mdef","node":{".class":"FuncDef","abstract_status":0,"arg_kinds":[0,1],"arg_names":["self","timeout"],"dataclass_transform_spec":null,"deprecated":null,"flags":["is_trivial_self"],"fullname":"qdrant_client.parallel_processor.ParallelWorkerPool.join_or_terminate","name":"join_or_terminate","type":{".class":"CallableType","arg_kinds":[0,1],"arg_names":["self","timeout"],"arg_types":["qdrant_client.parallel_processor.ParallelWorkerPool",{".class":"UnionType","items":["builtins.int",{".class":"NoneType"}],"uses_pep604_syntax":true}],"def_extras":{"first_arg":"self"},"fallback":"builtins.function","from_concatenate":false,"implicit":false,"imprecise_arg_kinds":false,"is_bound":false,"is_ellipsis_args":false,"name":"join_or_terminate of ParallelWorkerPool","ret_type":{".class":"NoneType"},"type_guard":null,"type_is":null,"unpack_kwargs":false,"variables":[]}}},"num_active_workers":{".class":"SymbolTableNode","implicit":true,"kind":"Mdef","node":{".class":"Var","flags":["explicit_self_type","is_ready","is_inferred"],"fullname":"qdrant_client.parallel_processor.ParallelWorkerPool.num_active_workers","name":"num_active_workers","setter_type":null,"type":{".class":"UnionType","items":[{".class":"Instance","args":[{".class":"AnyType","missing_import_name":null,"source_any":null,"type_of_any":4}],"extra_attrs":null,"type_ref":"multiprocessing.sharedctypes.Synchronized"},{".class":"NoneType"}],"uses_pep604_syntax":true}}},"num_workers":{".class":"SymbolTableNode","implicit":true,"kind":"Mdef","node":{".class":"Var","flags":["is_inferred"],"fullname":"qdrant_client.parallel_processor.ParallelWorkerPool.num_workers","name":"num_workers","setter_type":null,"type":"builtins.int"}},"ordered_map":{".class":"SymbolTableNode","kind":"Mdef","node":{".class":"FuncDef","abstract_status":0,"arg_kinds":[0,0,2,4],"arg_names":["self","stream","args","kwargs"],"dataclass_transform_spec":null,"deprecated":null,"flags":["is_trivial_self"],"fullname":"qdrant_client.parallel_processor.ParallelWorkerPool.ordered_map","name":"ordered_map","type":{".class":"CallableType","arg_kinds":[0,0,2,4],"arg_names":["self","stream","args","kwargs"],"arg_types":["qdrant_client.parallel_processor.ParallelWorkerPool",{".class":"Instance","args":[{".class":"AnyType","missing_import_name":null,"source_any":null,"type_of_any":2}],"extra_attrs":null,"type_ref":"typing.Iterable"},{".class":"AnyType","missing_import_name":null,"source_any":null,"type_of_any":2},{".class":"AnyType","missing_import_name":null,"source_any":null,"type_of_any":2}],"def_extras":{"first_arg":"self"},"fallback":"builtins.function","from_concatenate":false,"implicit":false,"imprecise_arg_kinds":false,"is_bound":false,"is_ellipsis_args":false,"name":"ordered_map of ParallelWorkerPool","ret_type":{".class":"Instance","args":[{".class":"AnyType","missing_import_name":null,"source_any":null,"type_of_any":2}],"extra_attrs":null,"type_ref":"typing.Iterable"},"type_guard":null,"type_is":null,"unpack_kwargs":false,"variables":[]}}},"output_queue":{".class":"SymbolTableNode","implicit":true,"kind":"Mdef","node":{".class":"Var","flags":["explicit_self_type","is_ready","is_inferred"],"fullname":"qdrant_client.parallel_processor.ParallelWorkerPool.output_queue","name":"output_queue","setter_type":null,"type":{".class":"UnionType","items":[{".class":"Instance","args":[{".class":"AnyType","missing_import_name":null,"source_any":null,"type_of_any":4}],"extra_attrs":null,"type_ref":"multiprocessing.queues.Queue"},{".class":"NoneType"}],"uses_pep604_syntax":true}}},"processes":{".class":"SymbolTableNode","implicit":true,"kind":"Mdef","node":{".class":"Var","flags":["explicit_self_type","is_ready","is_inferred"],"fullname":"qdrant_client.parallel_processor.ParallelWorkerPool.processes","name":"processes","setter_type":null,"type":{".class":"Instance","args":["multiprocessing.process.BaseProcess"],"extra_attrs":null,"type_ref":"builtins.list"}}},"queue_size":{".class":"SymbolTableNode","implicit":true,"kind":"Mdef","node":{".class":"Var","flags":["is_inferred"],"fullname":"qdrant_client.parallel_processor.ParallelWorkerPool.queue_size","name":"queue_size","setter_type":null,"type":"builtins.int"}},"semi_ordered_map":{".class":"SymbolTableNode","kind":"Mdef","node":{".class":"FuncDef","abstract_status":0,"arg_kinds":[0,0,2,4],"arg_names":["self","stream","args","kwargs"],"dataclass_transform_spec":null,"deprecated":null,"flags":["is_trivial_self"],"fullname":"qdrant_client.parallel_processor.ParallelWorkerPool.semi_ordered_map","name":"semi_ordered_map","type":{".class":"CallableType","arg_kinds":[0,0,2,4],"arg_names":["self","stream","args","kwargs"],"arg_types":["qdrant_client.parallel_processor.ParallelWorkerPool",{".class":"Instance","args":[{".class":"AnyType","missing_import_name":null,"source_any":null,"type_of_any":2}],"extra_attrs":null,"type_ref":"typing.Iterable"},{".class":"AnyType","missing_import_name":null,"source_any":null,"type_of_any":2},{".class":"AnyType","missing_import_name":null,"source_any":null,"type_of_any":2}],"def_extras":{"first_arg":"self"},"fallback":"builtins.function","from_concatenate":false,"implicit":false,"imprecise_arg_kinds":false,"is_bound":false,"is_ellipsis_args":false,"name":"semi_ordered_map of ParallelWorkerPool","ret_type":{".class":"Instance","args":[{".class":"AnyType","missing_import_name":null,"source_any":null,"type_of_any":2}],"extra_attrs":null,"type_ref":"typing.Iterable"},"type_guard":null,"type_is":null,"unpack_kwargs":false,"variables":[]}}},"start":{".class":"SymbolTableNode","kind":"Mdef","node":{".class":"FuncDef","abstract_status":0,"arg_kinds":[0,4],"arg_names":["self","kwargs"],"dataclass_transform_spec":null,"deprecated":null,"flags":["is_trivial_self"],"fullname":"qdrant_client.parallel_processor.ParallelWorkerPool.start","name":"start","type":{".class":"CallableType","arg_kinds":[0,4],"arg_names":["self","kwargs"],"arg_types":["qdrant_client.parallel_processor.ParallelWorkerPool",{".class":"AnyType","missing_import_name":null,"source_any":null,"type_of_any":2}],"def_extras":{"first_arg":"self"},"fallback":"builtins.function","from_concatenate":false,"implicit":false,"imprecise_arg_kinds":false,"is_bound":false,"is_ellipsis_args":false,"name":"start of ParallelWorkerPool","ret_type":{".class":"NoneType"},"type_guard":null,"type_is":null,"unpack_kwargs":false,"variables":[]}}},"unordered_map":{".class":"SymbolTableNode","kind":"Mdef","node":{".class":"FuncDef","abstract_status":0,"arg_kinds":[0,0,2,4],"arg_names":["self","stream","args","kwargs"],"dataclass_transform_spec":null,"deprecated":null,"flags":["is_trivial_self"],"fullname":"qdrant_client.parallel_processor.ParallelWorkerPool.unordered_map","name":"unordered_map","type":{".class":"CallableType","arg_kinds":[0,0,2,4],"arg_names":["self","stream","args","kwargs"],"arg_types":["qdrant_client.parallel_processor.ParallelWorkerPool",{".class":"Instance","args":[{".class":"AnyType","missing_import_name":null,"source_any":null,"type_of_any":2}],"extra_attrs":null,"type_ref":"typing.Iterable"},{".class":"AnyType","missing_import_name":null,"source_any":null,"type_of_any":2},{".class":"AnyType","missing_import_name":null,"source_any":null,"type_of_any":2}],"def_extras":{"first_arg":"self"},"fallback":"builtins.function","from_concatenate":false,"implicit":false,"imprecise_arg_kinds":false,"is_bound":false,"is_ellipsis_args":false,"name":"unordered_map of ParallelWorkerPool","ret_type":{".class":"Instance","args":[{".class":"AnyType","missing_import_name":null,"source_any":null,"type_of_any":2}],"extra_attrs":null,"type_ref":"typing.Iterable"},"type_guard":null,"type_is":null,"unpack_kwargs":false,"variables":[]}}},"worker_class":{".class":"SymbolTableNode","implicit":true,"kind":"Mdef","node":{".class":"Var","flags":["is_inferred"],"fullname":"qdrant_client.parallel_processor.ParallelWorkerPool.worker_class","name":"worker_class","setter_type":null,"type":{".class":"TypeType","item":"qdrant_client.parallel_processor.Worker"}}}},"self_type":{".class":"TypeVarType","default":{".class":"AnyType","missing_import_name":null,"source_any":null,"type_of_any":4},"fullname":"qdrant_client.parallel_processor.ParallelWorkerPool.Self","id":0,"name":"Self","namespace":"","upper_bound":"qdrant_client.parallel_processor.ParallelWorkerPool","values":[],"variance":0},"slots":null,"tuple_type":null,"type_vars":[],"typeddict_type":null}},"Queue":{".class":"SymbolTableNode","cross_ref":"multiprocessing.queues.Queue","kind":"Gdef"},"QueueSignals":{".class":"SymbolTableNode","kind":"Gdef","node":{".class":"TypeInfo","_promote":[],"abstract_attributes":[],"alt_promote":null,"bases":["builtins.str","enum.Enum"],"dataclass_transform_spec":null,"declared_metaclass":null,"defn":{".class":"ClassDef","fullname":"qdrant_client.parallel_processor.QueueSignals","name":"QueueSignals","type_vars":[]},"deletable_attributes":[],"deprecated":null,"flags":["is_enum"],"fullname":"qdrant_client.parallel_processor.QueueSignals","has_param_spec_type":false,"metaclass_type":"enum.EnumMeta","metadata":{},"module_name":"qdrant_client.parallel_processor","mro":["qdrant_client.parallel_processor.QueueSignals","builtins.str","typing.Sequence","typing.Reversible","typing.Collection","typing.Iterable","typing.Container","enum.Enum","builtins.object"],"names":{".class":"SymbolTable","confirm":{".class":"SymbolTableNode","kind":"Mdef","node":{".class":"Var","flags":["is_initialized_in_class","is_final","is_ready","is_inferred","has_explicit_value"],"fullname":"qdrant_client.parallel_processor.QueueSignals.confirm","name":"confirm","setter_type":null,"type":{".class":"Instance","args":[],"extra_attrs":null,"last_known_value":{".class":"LiteralType","fallback":"builtins.str","value":"confirm"},"type_ref":"builtins.str"}}},"error":{".class":"SymbolTableNode","kind":"Mdef","node":{".class":"Var","flags":["is_initialized_in_class","is_final","is_ready","is_inferred","has_explicit_value"],"fullname":"qdrant_client.parallel_processor.QueueSignals.error","name":"error","setter_type":null,"type":{".class":"Instance","args":[],"extra_attrs":null,"last_known_value":{".class":"LiteralType","fallback":"builtins.str","value":"error"},"type_ref":"builtins.str"}}},"stop":{".class":"SymbolTableNode","kind":"Mdef","node":{".class":"Var","flags":["is_initialized_in_class","is_final","is_ready","is_inferred","has_explicit_value"],"fullname":"qdrant_client.parallel_processor.QueueSignals.stop","name":"stop","setter_type":null,"type":{".class":"Instance","args":[],"extra_attrs":null,"last_known_value":{".class":"LiteralType","fallback":"builtins.str","value":"stop"},"type_ref":"builtins.str"}}}},"self_type":{".class":"TypeVarType","default":{".class":"AnyType","missing_import_name":null,"source_any":null,"type_of_any":4},"fullname":"qdrant_client.parallel_processor.QueueSignals.Self","id":0,"name":"Self","namespace":"","upper_bound":"qdrant_client.parallel_processor.QueueSignals","values":[],"variance":0},"slots":null,"tuple_type":null,"type_vars":[],"typeddict_type":null}},"Type":{".class":"SymbolTableNode","cross_ref":"typing.Type","kind":"Gdef"},"Worker":{".class":"SymbolTableNode","kind":"Gdef","node":{".class":"TypeInfo","_promote":[],"abstract_attributes":[],"alt_promote":null,"bases":["builtins.object"],"dataclass_transform_spec":null,"declared_metaclass":null,"defn":{".class":"ClassDef","fullname":"qdrant_client.parallel_processor.Worker","name":"Worker","type_vars":[]},"deletable_attributes":[],"deprecated":null,"flags":[],"fullname":"qdrant_client.parallel_processor.Worker","has_param_spec_type":false,"metaclass_type":null,"metadata":{},"module_name":"qdrant_client.parallel_processor","mro":["qdrant_client.parallel_processor.Worker","builtins.object"],"names":{".class":"SymbolTable","process":{".class":"SymbolTableNode","kind":"Mdef","node":{".class":"FuncDef","abstract_status":0,"arg_kinds":[0,0],"arg_names":["self","items"],"dataclass_transform_spec":null,"deprecated":null,"flags":["is_trivial_self"],"fullname":"qdrant_client.parallel_processor.Worker.process","name":"process","type":{".class":"CallableType","arg_kinds":[0,0],"arg_names":["self","items"],"arg_types":["qdrant_client.parallel_processor.Worker",{".class":"Instance","args":[{".class":"AnyType","missing_import_name":null,"source_any":null,"type_of_any":2}],"extra_attrs":null,"type_ref":"typing.Iterable"}],"def_extras":{"first_arg":"self"},"fallback":"builtins.function","from_concatenate":false,"implicit":false,"imprecise_arg_kinds":false,"is_bound":false,"is_ellipsis_args":false,"name":"process of Worker","ret_type":{".class":"Instance","args":[{".class":"AnyType","missing_import_name":null,"source_any":null,"type_of_any":2}],"extra_attrs":null,"type_ref":"typing.Iterable"},"type_guard":null,"type_is":null,"unpack_kwargs":false,"variables":[]}}},"start":{".class":"SymbolTableNode","kind":"Mdef","node":{".class":"Decorator","func":{".class":"FuncDef","abstract_status":0,"arg_kinds":[0,2,4],"arg_names":["cls","args","kwargs"],"dataclass_transform_spec":null,"deprecated":null,"flags":["is_class","is_decorated","is_trivial_self"],"fullname":"qdrant_client.parallel_processor.Worker.start","name":"start","type":{".class":"CallableType","arg_kinds":[0,2,4],"arg_names":["cls","args","kwargs"],"arg_types":[{".class":"TypeType","item":"qdrant_client.parallel_processor.Worker"},{".class":"AnyType","missing_import_name":null,"source_any":null,"type_of_any":2},{".class":"AnyType","missing_import_name":null,"source_any":null,"type_of_any":2}],"def_extras":{"first_arg":"cls"},"fallback":"builtins.function","from_concatenate":false,"implicit":false,"imprecise_arg_kinds":false,"is_bound":false,"is_ellipsis_args":false,"name":"start of Worker","ret_type":"qdrant_client.parallel_processor.Worker","type_guard":null,"type_is":null,"unpack_kwargs":false,"variables":[]}},"is_overload":false,"var":{".class":"Var","flags":["is_initialized_in_class","is_classmethod","is_ready","is_inferred"],"fullname":"qdrant_client.parallel_processor.Worker.start","name":"start","setter_type":null,"type":{".class":"CallableType","arg_kinds":[0,2,4],"arg_names":["cls","args","kwargs"],"arg_types":[{".class":"TypeType","item":"qdrant_client.parallel_processor.Worker"},{".class":"AnyType","missing_import_name":null,"source_any":null,"type_of_any":2},{".class":"AnyType","missing_import_name":null,"source_any":null,"type_of_any":2}],"def_extras":{"first_arg":"cls"},"fallback":"builtins.function","from_concatenate":false,"implicit":false,"imprecise_arg_kinds":false,"is_bound":false,"is_ellipsis_args":false,"name":"start of Worker","ret_type":"qdrant_client.parallel_processor.Worker","type_guard":null,"type_is":null,"unpack_kwargs":false,"variables":[]}}}}},"self_type":{".class":"TypeVarType","default":{".class":"AnyType","missing_import_name":null,"source_any":null,"type_of_any":4},"fullname":"qdrant_client.parallel_processor.Worker.Self","id":0,"name":"Self","namespace":"","upper_bound":"qdrant_client.parallel_processor.Worker","values":[],"variance":0},"slots":null,"tuple_type":null,"type_vars":[],"typeddict_type":null}},"__annotations__":{".class":"SymbolTableNode","kind":"Gdef","node":{".class":"Var","flags":["is_ready"],"fullname":"qdrant_client.parallel_processor.__annotations__","name":"__annotations__","setter_type":null,"type":{".class":"Instance","args":["builtins.str",{".class":"AnyType","missing_import_name":null,"source_any":null,"type_of_any":6}],"extra_attrs":null,"type_ref":"builtins.dict"}}},"__doc__":{".class":"SymbolTableNode","kind":"Gdef","node":{".class":"Var","flags":["is_ready"],"fullname":"qdrant_client.parallel_processor.__doc__","name":"__doc__","setter_type":null,"type":"builtins.str"}},"__file__":{".class":"SymbolTableNode","kind":"Gdef","node":{".class":"Var","flags":["is_ready"],"fullname":"qdrant_client.parallel_processor.__file__","name":"__file__","setter_type":null,"type":"builtins.str"}},"__name__":{".class":"SymbolTableNode","kind":"Gdef","node":{".class":"Var","flags":["is_ready"],"fullname":"qdrant_client.parallel_processor.__name__","name":"__name__","setter_type":null,"type":"builtins.str"}},"__package__":{".class":"SymbolTableNode","kind":"Gdef","node":{".class":"Var","flags":["is_ready"],"fullname":"qdrant_client.parallel_processor.__package__","name":"__package__","setter_type":null,"type":"builtins.str"}},"__spec__":{".class":"SymbolTableNode","kind":"Gdef","node":{".class":"Var","flags":["is_ready"],"fullname":"qdrant_client.parallel_processor.__spec__","name":"__spec__","setter_type":null,"type":"_frozen_importlib.ModuleSpec"}},"_worker":{".class":"SymbolTableNode","kind":"Gdef","node":{".class":"FuncDef","abstract_status":0,"arg_kinds":[0,0,0,0,0,1],"arg_names":["worker_class","input_queue","output_queue","num_active_workers","worker_id","kwargs"],"dataclass_transform_spec":null,"deprecated":null,"flags":[],"fullname":"qdrant_client.parallel_processor._worker","name":"_worker","type":{".class":"CallableType","arg_kinds":[0,0,0,0,0,1],"arg_names":["worker_class","input_queue","output_queue","num_active_workers","worker_id","kwargs"],"arg_types":[{".class":"TypeType","item":"qdrant_client.parallel_processor.Worker"},{".class":"Instance","args":[{".class":"AnyType","missing_import_name":null,"source_any":null,"type_of_any":4}],"extra_attrs":null,"type_ref":"multiprocessing.queues.Queue"},{".class":"Instance","args":[{".class":"AnyType","missing_import_name":null,"source_any":null,"type_of_any":4}],"extra_attrs":null,"type_ref":"multiprocessing.queues.Queue"},{".class":"Instance","args":[{".class":"AnyType","missing_import_name":null,"source_any":null,"type_of_any":4}],"extra_attrs":null,"type_ref":"multiprocessing.sharedctypes.Synchronized"},"builtins.int",{".class":"UnionType","items":[{".class":"Instance","args":["builtins.str",{".class":"AnyType","missing_import_name":null,"source_any":null,"type_of_any":2}],"extra_attrs":null,"type_ref":"builtins.dict"},{".class":"NoneType"}],"uses_pep604_syntax":true}],"def_extras":{"first_arg":null},"fallback":"builtins.function","from_concatenate":false,"implicit":false,"imprecise_arg_kinds":false,"is_bound":false,"is_ellipsis_args":false,"name":"_worker","ret_type":{".class":"NoneType"},"type_guard":null,"type_is":null,"unpack_kwargs":false,"variables":[]}}},"defaultdict":{".class":"SymbolTableNode","cross_ref":"collections.defaultdict","kind":"Gdef"},"get_context":{".class":"SymbolTableNode","cross_ref":"multiprocessing.get_context","kind":"Gdef"},"logging":{".class":"SymbolTableNode","cross_ref":"logging","kind":"Gdef"},"os":{".class":"SymbolTableNode","cross_ref":"os","kind":"Gdef"},"processing_timeout":{".class":"SymbolTableNode","kind":"Gdef","node":{".class":"Var","flags":["is_ready","is_inferred","has_explicit_value"],"fullname":"qdrant_client.parallel_processor.processing_timeout","name":"processing_timeout","setter_type":null,"type":"builtins.int"}}},"path":"C:\\Users\\ksree\\anaconda3\\Lib\\site-packages\\qdrant_client\\parallel_processor.py"}